{
    "version": "https://jsonfeed.org/version/1",
    "title": "CatIsNotFound • All posts by \"waline\" tag",
    "description": "一个基于 Hexo 框架的个人博客网站",
    "home_page_url": "https://CatIsNotFound.github.io",
    "items": [
        {
            "id": "https://catisnotfound.github.io/2024/06/20/Ver-1-3-CatIsNotFound-%E6%9B%B4%E6%96%B0%E6%97%A5%E5%BF%97/",
            "url": "https://catisnotfound.github.io/2024/06/20/Ver-1-3-CatIsNotFound-%E6%9B%B4%E6%96%B0%E6%97%A5%E5%BF%97/",
            "title": "[Ver 1.3] CatIsNotFound 更新日志",
            "date_published": "2024-06-20T04:31:43.000Z",
            "content_html": "\n  <div class=\"note-large blue\">\n    <div class=\"notel-title rounded-t-lg p-3 font-bold text-lg flex flex-row gap-2 items-center\">\n      <i class=\"notel-icon fa-solid fa-solid fa-book\"></i><p>写在最前</p>\n\n    </div>\n    <div class=\"notel-content\">\n      <p>仅此两三周的时间，博客站点又迎来了一次更新。以下是关于本博客站点的更新内容。</p>\n<p><img loading=\"lazy\" src=\"/images/2024/0620/cover.jpg\"></p>\n\n    </div>\n  </div>\n\n<h1 id=\"新增内容\"><a href=\"#新增内容\" class=\"headerlink\" title=\"新增内容\"></a>新增内容</h1><h2 id=\"博客-Logo\"><a href=\"#博客-Logo\" class=\"headerlink\" title=\"博客 Logo\"></a>博客 Logo</h2><p>在本次更新中，本人新增了一个博客站点 Logo；这是基于一张《夏日友人帐》中的猫咪老师的形象而绘制的。</p>\n<p><img loading=\"lazy\" src=\"/images/logo.png\" alt=\"Logo\"></p>\n<p><strong>如果此 Logo 存在任何侵权，请直接在评论区下方或者联系本人进行删除。</strong></p>\n<h1 id=\"页面更新\"><a href=\"#页面更新\" class=\"headerlink\" title=\"页面更新\"></a>页面更新</h1><p>很显然，这次的博客站点更新了一些页面，下面将简要介绍：</p>\n<h2 id=\"首页\"><a href=\"#首页\" class=\"headerlink\" title=\"首页\"></a>首页</h2><ul>\n<li><p>首页页面下不仅仅只是更新了背景图和轮播文字（打字机效果），还简要地将侧边导航栏、个人信息栏、文章列表做了对调，使得更倾向于先看文章标题及摘要。</p>\n</li>\n<li><p>同时，头部导航栏以及侧边导航栏已作出修改；使得更容易翻阅每篇文章；</p>\n</li>\n</ul>\n<p><img loading=\"lazy\" src=\"/images/2024/0620/1.jpg\" alt=\"首页2\"></p>\n<h2 id=\"文章页面\"><a href=\"#文章页面\" class=\"headerlink\" title=\"文章页面\"></a>文章页面</h2><ul>\n<li><p>文章页面底部新增 [自动推荐] 栏目（基于 Nodejieba 算法），你可以在文章页面下方选择推荐的文章；</p>\n</li>\n<li><p>文章页面底部新增 <strong>[表情反应]</strong> 界面，你可以在对应文章的下方选择你的表情反应；</p>\n</li>\n</ul>\n<p><img loading=\"lazy\" src=\"/images/2024/0620/2.jpg\" alt=\"表情反应\"></p>\n\n  <div class=\"note-large blue\">\n    <div class=\"notel-title rounded-t-lg p-3 font-bold text-lg flex flex-row gap-2 items-center\">\n      <i class=\"notel-icon fa-solid fa-solid fa-info-circle\"></i><p>关于评论</p>\n\n    </div>\n    <div class=\"notel-content\">\n      <p>你可以在此站点上发表评论，但由于 Waline 评论系统的限制，你将无法正常收到任何邮件通知。因此，若遇到问题或有任何建议，请直接通过电子邮件、知乎、B站私信等方式联系本人。</p>\n\n    </div>\n  </div>\n\n<h1 id=\"未来计划\"><a href=\"#未来计划\" class=\"headerlink\" title=\"未来计划\"></a>未来计划</h1><p>与之前的更新日志一样，本站点的未来计划也很简单：</p>\n<ul>\n<li><p>继续完善博客站点的功能，包括文章分类、标签、搜索功能等；</p>\n</li>\n<li><p>继续创作博客文章，目前暂未达到 20 篇博客文章了。<del>（即使有一部分是水出来的，bushi😅）</del></p>\n</li>\n</ul>\n\n  <div class=\"note-large green\">\n    <div class=\"notel-title rounded-t-lg p-3 font-bold text-lg flex flex-row gap-2 items-center\">\n      <i class=\"notel-icon fa-solid fa-solid fa-info-circle\"></i><p>更新日志链接</p>\n\n    </div>\n    <div class=\"notel-content\">\n      <p>关于 Redefine 主题的更新内容，请直接访问以下链接：</p>\n<p>🔗 <a class=\"link\"   href=\"https://github.com/EvanNotFound/hexo-theme-redefine/releases\" >https://github.com/EvanNotFound/hexo-theme-redefine/releases <i class=\"fa-regular fa-arrow-up-right-from-square fa-sm\"></i></a></p>\n\n    </div>\n  </div>",
            "tags": [
                "更新日志",
                "Waline"
            ]
        },
        {
            "id": "https://catisnotfound.github.io/2024/06/02/%E6%90%AD%E5%BB%BA%E4%B8%AA%E4%BA%BA%E5%8D%9A%E5%AE%A2%EF%BC%88%E5%9B%9B%EF%BC%89%EF%BC%9A%E5%A6%82%E4%BD%95%E5%AE%9E%E7%8E%B0%E8%AF%84%E8%AE%BA%E7%B3%BB%E7%BB%9F/",
            "url": "https://catisnotfound.github.io/2024/06/02/%E6%90%AD%E5%BB%BA%E4%B8%AA%E4%BA%BA%E5%8D%9A%E5%AE%A2%EF%BC%88%E5%9B%9B%EF%BC%89%EF%BC%9A%E5%A6%82%E4%BD%95%E5%AE%9E%E7%8E%B0%E8%AF%84%E8%AE%BA%E7%B3%BB%E7%BB%9F/",
            "title": "搭建个人博客（四）：如何实现评论系统",
            "date_published": "2024-06-02T12:00:00.000Z",
            "content_html": "\n  <div class=\"note-large default\">\n    <div class=\"notel-title rounded-t-lg p-3 font-bold text-lg flex flex-row gap-2 items-center\">\n      <i class=\"notel-icon fa-solid fa-solid fa-comment\"></i><p>前言</p>\n\n    </div>\n    <div class=\"notel-content\">\n      <p>评论系统是博客中不可或缺的一部分，它能够让读者与作者互动，提高博客的互动性。目前针对 Hexo 博客，Waline 评论系统是目前比较流行的评论系统。</p>\n<p><img loading=\"lazy\" src=\"/images/2024/0602/waline.jpg\"></p>\n\n    </div>\n  </div>\n\n\n  <div class=\"note-large yellow\">\n    <div class=\"notel-title rounded-t-lg p-3 font-bold text-lg flex flex-row gap-2 items-center\">\n      <i class=\"notel-icon fa-solid fa-solid fa-exclamation-triangle\"></i><p>观前注意</p>\n\n    </div>\n    <div class=\"notel-content\">\n      <p>在开始部署之前，假如之前还未部署过 Hexo 博客，请直接跳转到 <a href=\"/2024/04/23/%E6%90%AD%E5%BB%BA%E4%B8%AA%E4%BA%BA%E5%8D%9A%E5%AE%A2%EF%BC%88%E4%B8%80%EF%BC%89%EF%BC%9A%E5%A6%82%E4%BD%95%E5%9C%A8-Github-Page-%E4%B8%8A%E6%90%AD%E5%BB%BA%E6%88%91%E7%9A%84%E4%B8%AA%E4%BA%BA%E5%8D%9A%E5%AE%A2/\" title=\"搭建个人博客（一）：如何在 Github Page 上搭建我的个人博客\">搭建个人博客（一）：如何在 Github Page 上搭建我的个人博客</a> 进行部署。</p>\n<p>其次，本文主要针对于 Redifine 主题的评论系统部署，<strong>其他主题的评论系统部署方式可能有所不同</strong>，具体请参考对应主题的说明文档。</p>\n\n    </div>\n  </div>\n\n\n\n<h1 id=\"Deta-部署评论系统\"><a href=\"#Deta-部署评论系统\" class=\"headerlink\" title=\"Deta 部署评论系统\"></a>Deta 部署评论系统</h1><p>本文根据 Deta 部署 Waline 评论系统，其他部署方式请参考 Waline 官方文档。</p>\n<h2 id=\"1-注册-Deta-账号\"><a href=\"#1-注册-Deta-账号\" class=\"headerlink\" title=\"1. 注册 Deta 账号\"></a>1. 注册 Deta 账号</h2><a class=\"button  large center\" href='https://deta.sh/signup' title='注册 Deta 账号'><i class='fa-solid fa-sign-in-alt'></i> 注册 Deta 账号</a>\n\n<p>在部署之前，你需要先注册 Deta 账号。</p>\n<h2 id=\"2-安装-Waline-插件\"><a href=\"#2-安装-Waline-插件\" class=\"headerlink\" title=\"2. 安装 Waline 插件\"></a>2. 安装 Waline 插件</h2><a class=\"button  large center\" href='https://deta.space/discovery/@lizheming/waline' title='Install Waline to Deta'><i class='fa-solid fa-cloud-upload-alt'></i> Install Waline to Deta</a>\n\n<p>请先点击上方按钮，然后再如下页面中，选择 <code>Install on Space</code> 按钮，等待一段时间后就能完成安装。</p>\n<p><img loading=\"lazy\" src=\"https://waline.js.org/assets/deta-b3wwcCqL.png\" alt=\"Deta 主页\"></p>\n<p>之后，你将能直接在你的 Space 中看到 Waline 评论系统。</p>\n<a class=\"button  regular center\" href='https://deta.space' title='访问你的 Deta Space'><i class='fa-solid fa-cloud'></i> 访问你的 Deta Space</a>\n\n<p>在自己的 Deta Space 中，鼠标移动到 Waline，点击这里左上角的设置按钮图标，点击 <code>Open App</code> 选项，查看能否成功访问到 App 页面。</p>\n<img loading=\"lazy\" src=\"/images/2024/0602/1.jpg\" alt=\"\" style=\"zoom:50%;\" />\n\n<h2 id=\"3-配置-Waline-到你的博客\"><a href=\"#3-配置-Waline-到你的博客\" class=\"headerlink\" title=\"3. 配置 Waline 到你的博客\"></a>3. 配置 Waline 到你的博客</h2><p>请先在自己的 Deta Space 中，点击 Waline 左上角的设置按钮图标，然后点击 <code>Open Settings</code> 选项。</p>\n<p>在如下图的 <code>Domains</code> 选项卡中，复制蓝色字中的域名。</p>\n<img loading=\"lazy\" src=\"/images/2024/0602/3.jpg\" alt=\"\" style=\"zoom:75%;\" />\n\n<p>之后，请在你的博客仓库的根目录下，找到 <code>_config.redefine.yml</code> 文件，找到如下内容，并修改其对应的 <code>serverUrl</code> 选项即可。</p>\n\n  <div class=\"note-large yellow\">\n    <div class=\"notel-title rounded-t-lg p-3 font-bold text-lg flex flex-row gap-2 items-center\">\n      <i class=\"notel-icon fa-solid fa-solid fa-exclamation-triangle\"></i><p>警告</p>\n\n    </div>\n    <div class=\"notel-content\">\n      <p>不同的主题，配置的方式有所不同。如果你使用的是其他主题，请自行参考对应主题的说明文档。</p>\n\n    </div>\n  </div>\n\n<div class=\"highlight-container\" data-rel=\"Yaml\"><figure class=\"iseeu highlight yaml\"><table><tr><td class=\"gutter\"><pre><span class=\"line\">1</span><br><span class=\"line\">2</span><br><span class=\"line\">3</span><br><span class=\"line\">4</span><br><span class=\"line\">5</span><br><span class=\"line\">6</span><br><span class=\"line\">7</span><br><span class=\"line\">8</span><br></pre></td><td class=\"code\"><pre><span class=\"line\"><span class=\"comment\"># COMMENT &gt;&gt;&gt;&gt;&gt;&gt;&gt;&gt;&gt;&gt;&gt;&gt;&gt;&gt;&gt;&gt;&gt;&gt;&gt;&gt;&gt;&gt;&gt;&gt;&gt;&gt;&gt;&gt;&gt;&gt;&gt;&gt;&gt;&gt;&gt;&gt;&gt;&gt;&gt;&gt;&gt;&gt;&gt;&gt;&gt;&gt;&gt;&gt;&gt;&gt;&gt;&gt;&gt;&gt;&gt;&gt;&gt;&gt;&gt;&gt;&gt;&gt;&gt;&gt;&gt;&gt;&gt;&gt;&gt;&gt; start</span></span><br><span class=\"line\"><span class=\"comment\"># Docs: https://redefine-docs.ohevan.com/posts/comment</span></span><br><span class=\"line\"><span class=\"attr\">comment:</span></span><br><span class=\"line\">  <span class=\"attr\">config:</span></span><br><span class=\"line\">    <span class=\"comment\"># Waline comment system. See https://waline.js.org/</span></span><br><span class=\"line\">    <span class=\"attr\">waline:</span></span><br><span class=\"line\">      <span class=\"attr\">serverUrl:</span> <span class=\"string\">https://**************</span> <span class=\"comment\"># 在 * 处粘贴你的 Deta 域名</span></span><br><span class=\"line\">      <span class=\"attr\">lang:</span> <span class=\"string\">zh-CN</span> <span class=\"comment\"># Waline language. e.g. zh-CN, en-US. See https://waline.js.org/guide/client/i18n.html</span></span><br></pre></td></tr></table></figure></div>\n\n<h2 id=\"4-测试你的评论\"><a href=\"#4-测试你的评论\" class=\"headerlink\" title=\"4. 测试你的评论\"></a>4. 测试你的评论</h2><p>请在你的本地上运行 <code>npx hexo server</code> 命令，然后访问你的博客。在任意一篇文章页面下方，进行评论吧！</p>\n<a class=\"button  large center\" href='http://localhost:4000' title='访问我的个人网站'><i class='fa-solid fa-link'></i> 访问我的个人网站</a>\n\n<h1 id=\"查看-管理评论\"><a href=\"#查看-管理评论\" class=\"headerlink\" title=\"查看&#x2F;管理评论\"></a>查看&#x2F;管理评论</h1><p>关于此内容，若你已经完成部署且成功发出评论后，你可以按照以下方式查看或管理评论。当然你还可以设置邮箱提醒功能，当有访客评论你的文章时，你将会收到邮件提醒。</p>\n<h2 id=\"在-Waline-中管理-查看评论\"><a href=\"#在-Waline-中管理-查看评论\" class=\"headerlink\" title=\"在 Waline 中管理&#x2F;查看评论\"></a>在 Waline 中管理&#x2F;查看评论</h2><p>首先进入你的博客，在任意一篇文章页面下方，点击 <code>登录</code> 按钮，在弹出的登录页面里，请使用 Github 账号以快捷登录。</p>\n<img loading=\"lazy\" src=\"/images/2024/0602/2.jpg\" alt=\"\" style=\"zoom:60%;\" />\n\n<img loading=\"lazy\" src=\"/images/2024/0602/6.jpg\" alt=\"\" style=\"zoom:60%;\" />\n\n<p>登录成功后，你可以直接点击左上角的【管理】→ 【评论】，以查看所有评论。</p>\n<img loading=\"lazy\" src=\"/images/2024/0602/7.jpg\" alt=\"\" style=\"zoom:80%;\" />\n\n<p>你还可以点击左上角的【管理】→ 【用户】，以管理用户。</p>\n<img loading=\"lazy\" src=\"/images/2024/0602/8.jpg\" alt=\"\" style=\"zoom:80%;\" />\n\n<h2 id=\"在-Deta-中查看评论\"><a href=\"#在-Deta-中查看评论\" class=\"headerlink\" title=\"在 Deta 中查看评论\"></a>在 Deta 中查看评论</h2><p>首先进入你的 Deta Space，点击 Waline 应用，然后点击 <code>View App Data</code> 按钮，在此页面中，你可以看到所有评论的详细信息。</p>\n<img loading=\"lazy\" src=\"/images/2024/0602/4.jpg\" alt=\"\" style=\"zoom:80%;\" />\n\n<p>其中，该页面中，有以下两个表 <code>Comment</code> 和 <code>Users</code> 表，分别存储了评论信息和用户信息。</p>\n<p>以下是每个表内对应列的含义：</p>\n<ul>\n<li><code>Comment</code> 表：<ul>\n<li><code>key</code>: 评论的唯一标识符</li>\n<li><code>comment</code>: 评论内容</li>\n<li><code>insertAt</code>: 评论时间</li>\n<li><code>ip</code>: 评论者 IP 地址</li>\n<li><code>likes</code>: 点赞数（默认为空）</li>\n<li><code>mail</code>: 评论者邮箱</li>\n<li><code>nick</code>: 评论者昵称</li>\n<li><code>objectId</code>: 评论所属文章的唯一标识符</li>\n<li><code>status</code>: 评论状态（默认 <code>approved</code> 表示正常）</li>\n<li><code>ua</code>: 评论者浏览器信息</li>\n<li><code>url</code>: 当前评论文章页面的 URL</li>\n<li><code>user_id</code>: 评论者的唯一标识符</li>\n<li>…</li>\n</ul>\n</li>\n<li><code>Users</code> 表：<ul>\n<li><code>key</code>: 用户的唯一标识符</li>\n<li><code>avatar</code>: 用户头像 URL</li>\n<li><code>display_name</code>: 用户昵称</li>\n<li><code>email</code>: 用户邮箱</li>\n<li><code>label</code>: 用户标签（默认为空）</li>\n<li><code>objectId</code>: 用户唯一标识符</li>\n<li><code>password</code>: 用户密码（已被加密）</li>\n<li><code>qq</code>: 第三方授权 QQ 号（用户若已绑定 QQ）</li>\n<li><code>type</code>: 用户类型（默认 <code>guest</code> 表示普通用户）</li>\n<li><code>url</code>: 用户主页 URL</li>\n<li><code>github</code>: 第三方授权 GitHub 账号（用户若已绑定 GitHub）</li>\n</ul>\n</li>\n</ul>\n<h1 id=\"附加功能\"><a href=\"#附加功能\" class=\"headerlink\" title=\"附加功能\"></a>附加功能</h1><h2 id=\"邮件提醒\"><a href=\"#邮件提醒\" class=\"headerlink\" title=\"邮件提醒\"></a>邮件提醒</h2><p>Waline 评论系统支持邮件提醒功能，当其它访客访问你的博客时，并且在某篇文章的评论区留言时，会收到邮件提醒。</p>\n<p>为了实现这个功能，你需要在 Deta Space 中，找到 Waline 应用，然后点击 <code>Open Settings</code> 按钮，在 <code>Configuraion</code> 选项卡中，找到如下变量并输入对应的值即可。</p>\n<img loading=\"lazy\" src=\"/images/2024/0602/5.jpg\" alt=\"\" style=\"zoom:80%;\" />\n\n<p>邮件通知需要配置以下环境变量：（<strong>以下变量均为必填</strong>）</p>\n<ul>\n<li><code>SMTP_SERVICE</code>: SMTP 邮件发送服务提供商。</li>\n</ul>\n\n  <div class=\"note-large blue\">\n    <div class=\"notel-title rounded-t-lg p-3 font-bold text-lg flex flex-row gap-2 items-center\">\n      <i class=\"notel-icon fa-solid fa-solid fa-info-circle\"></i><p>提示</p>\n\n    </div>\n    <div class=\"notel-content\">\n      <p>你可以点击下方的按钮，在这里找到 SMTP 邮件发送服务提供商的列表，并查看所有支持的运营商。</p>\n<p><a class=\"button  large center\" href='https://github.com/nodemailer/nodemailer/blob/master/lib/well-known/services.json' title='点击此处查看 SMTP 邮件发送服务提供商列表'><i class='fa-solid fa-link'></i> 点击此处查看 SMTP 邮件发送服务提供商列表</a></p>\n\n    </div>\n  </div>\n\n<ul>\n<li><code>SMTP_HOST</code>: SMTP 服务器地址（必填）</li>\n<li><code>SMTP_PORT</code>: SMTP 服务器端口（必填）</li>\n<li><code>SMTP_USER</code>: SMTP 邮件发送服务的用户名，一般为登录邮箱。</li>\n<li><code>SMTP_PASS</code>: SMTP 邮件发送服务的密码，一般为邮箱登录密码，部分邮箱(例如 163、qq)需要使用授权码。</li>\n<li><code>SITE_NAME</code>: 网站名称，用于在消息中显示。</li>\n<li><code>SITE_URL</code>: 网站地址，用于在消息中显示。</li>\n<li><code>AUTHOR_EMAIL</code>: 博主邮箱，用来接收新评论通知。如果是博主发布的评论则不进行提醒通知。</li>\n</ul>\n<p>配置完以上配置后，使用鼠标滚轮滚到最底，并点击 <code>Save Change</code> 按钮，若左上角提示 <code>Presets saved</code> 则表示配置成功。</p>\n<p>接下来，只需要回到你的博客网站，使用任意其它用户的身份在评论区留言，其它访客访问你的博客时，你将会收到邮件提醒。</p>\n<h2 id=\"Emoji-表情\"><a href=\"#Emoji-表情\" class=\"headerlink\" title=\"Emoji 表情\"></a>Emoji 表情</h2><p>你可以像如下图所示的那样，在你的博客中加入 Emoji 表情。</p>\n<img loading=\"lazy\" src=\"/images/2024/0602/comment.jpg\" alt=\"\" style=\"zoom:85%;\" />\n\n<p>如果你需要进行添加 Emoji 表情，请直接在 <code>_config.redefine.yml</code> 文件中，找到 <code>emoji</code> 选项，并添加对应的 URL 即可。</p>\n<div class=\"highlight-container\" data-rel=\"Yml\"><figure class=\"iseeu highlight yml\"><table><tr><td class=\"gutter\"><pre><span class=\"line\">1</span><br><span class=\"line\">2</span><br><span class=\"line\">3</span><br><span class=\"line\">4</span><br><span class=\"line\">5</span><br><span class=\"line\">6</span><br><span class=\"line\">7</span><br><span class=\"line\">8</span><br><span class=\"line\">9</span><br><span class=\"line\">10</span><br><span class=\"line\">11</span><br><span class=\"line\">12</span><br><span class=\"line\">13</span><br></pre></td><td class=\"code\"><pre><span class=\"line\"><span class=\"comment\"># COMMENT &gt;&gt;&gt;&gt;&gt;&gt;&gt;&gt;&gt;&gt;&gt;&gt;&gt;&gt;&gt;&gt;&gt;&gt;&gt;&gt;&gt;&gt;&gt;&gt;&gt;&gt;&gt;&gt;&gt;&gt;&gt;&gt;&gt;&gt;&gt;&gt;&gt;&gt;&gt;&gt;&gt;&gt;&gt;&gt;&gt;&gt;&gt;&gt;&gt;&gt;&gt;&gt;&gt;&gt;&gt;&gt;&gt;&gt;&gt;&gt;&gt;&gt;&gt;&gt;&gt;&gt;&gt;&gt;&gt;&gt; start</span></span><br><span class=\"line\"><span class=\"comment\"># Docs: https://redefine-docs.ohevan.com/posts/comment</span></span><br><span class=\"line\"><span class=\"attr\">comment:</span></span><br><span class=\"line\">  <span class=\"attr\">config:</span></span><br><span class=\"line\">    <span class=\"comment\"># Waline comment system. See https://waline.js.org/</span></span><br><span class=\"line\">    <span class=\"attr\">waline:</span></span><br><span class=\"line\">      <span class=\"attr\">emoji:</span> [</span><br><span class=\"line\">        <span class=\"string\">&#x27;https://unpkg.com/@waline/emojis@1.2.0/bmoji&#x27;</span>,</span><br><span class=\"line\">        <span class=\"string\">&#x27;https://unpkg.com/@waline/emojis@1.2.0/weibo&#x27;</span>,</span><br><span class=\"line\">        <span class=\"string\">&#x27;https://unpkg.com/@waline/emojis@1.2.0/qq&#x27;</span>,</span><br><span class=\"line\">        <span class=\"string\">&#x27;https://unpkg.com/@waline/emojis@1.2.0/soul-emoji&#x27;</span>,</span><br><span class=\"line\">        <span class=\"string\">&#x27;https://unpkg.com/@waline/emojis@1.2.0/tw-emoji&#x27;</span></span><br><span class=\"line\">      ] <span class=\"comment\"># 请以数组的方式添加 Emoji 表情的 URL</span></span><br></pre></td></tr></table></figure></div>\n\n<p>关于 Emoji 表情的更多信息，请<a class=\"link\"   href=\"https://waline.js.org/guide/features/emoji.html\" >参考 Waline 官方文档 <i class=\"fa-regular fa-arrow-up-right-from-square fa-sm\"></i></a>。</p>\n\n  <div class=\"note-large green\">\n    <div class=\"notel-title rounded-t-lg p-3 font-bold text-lg flex flex-row gap-2 items-center\">\n      <i class=\"notel-icon fa-solid fa-solid fa-book\"></i><p>参考链接</p>\n\n    </div>\n    <div class=\"notel-content\">\n      <p>🔗 <a class=\"link\"   href=\"https://redefine-docs.ohevan.com/posts/comment\" >https://redefine-docs.ohevan.com/posts/comment <i class=\"fa-regular fa-arrow-up-right-from-square fa-sm\"></i></a><br>🔗 <a class=\"link\"   href=\"https://waline.js.org/guide/get-started/\" >https://waline.js.org/guide/get-started/ <i class=\"fa-regular fa-arrow-up-right-from-square fa-sm\"></i></a><br>🔗 <a class=\"link\"   href=\"https://waline.js.org/guide/deploy/deta.html\" >https://waline.js.org/guide/deploy/deta.html <i class=\"fa-regular fa-arrow-up-right-from-square fa-sm\"></i></a><br>🔗 <a class=\"link\"   href=\"https://waline.js.org/guide/features/emoji.html\" >https://waline.js.org/guide/features/emoji.html <i class=\"fa-regular fa-arrow-up-right-from-square fa-sm\"></i></a><br>🔗 <a class=\"link\"   href=\"https://waline.js.org/guide/features/notification.html\" >https://waline.js.org/guide/features/notification.html <i class=\"fa-regular fa-arrow-up-right-from-square fa-sm\"></i></a></p>\n\n    </div>\n  </div>\n",
            "tags": [
                "Waline",
                "博客搭建"
            ]
        }
    ]
}